Metadata-Version: 2.1
Name: indent-tools
Version: 2.0
Summary: Tools for text indentation and XML/HTML markup generation.
Home-page: https://github.com/lainproliant/indent-tools
Author: Lain Musgrove (lainproliant)
Author-email: lainproliant@gmail.com
License: MIT
Keywords: indent text formatting xml html
Classifier: Development Status :: 5 - Production/Stable
Classifier: Intended Audience :: Developers
Classifier: License :: OSI Approved :: MIT License
Classifier: Topic :: Software Development :: Libraries :: Application Frameworks
Classifier: Programming Language :: Python :: 3
License-File: LICENSE
